sgcm/__init__.py
sgcm/module.py
sgcm-0.1.2.dist-info/licenses/LICENSE
sgcm-0.1.2.dist-info/METADATA
sgcm-0.1.2.dist-info/WHEEL
sgcm-0.1.2.dist-info/top_level.txt
sgcm-0.1.2.dist-info/RECORD
